pythonProject/__init__.py
pythonProject/phishing.py
pythonProject/settings.py
pythonProject/setup.py
pythonProject/test.py
pythonProject/Plugins/core.py
pythonProject/Plugins/dga_engine.py
pythonProject/Plugins/http_port.py
pythonProject/Plugins/punycode.py
pythonProject/Plugins/zero_width.py
pythonProject/build/lib/gib/__init__.py
pythonProject/build/lib/gib/gib_detect.py
pythonProject/build/lib/gib/gib_detect_train.py
pythonProject/gib/__init__.py
pythonProject/gib/gib_detect.py
pythonProject/gib/gib_detect_train.py
pythonProject/venv/Scripts/activate_this.py
detect_url-0.0.1.dist-info/METADATA
detect_url-0.0.1.dist-info/WHEEL
detect_url-0.0.1.dist-info/top_level.txt
detect_url-0.0.1.dist-info/RECORD
