Metadata-Version: 2.1
Name: detect-url
Version: 0.0.1
Summary: Package to detect and identify maliciousness in URL links}
Author-email: Russell Yap <russellyaplong@example.com>
Classifier: Programming Language :: Python :: 3
Classifier: License :: OSI Approved :: MIT License
Classifier: Operating System :: OS Independent
Requires-Python: >=3.7
